[
  {
    "type": "input",
    "name": "firstName",
    "placeholder": "Deymer",
    "label": "First name",
    "value": "Lorem",
    "validations": [
      {
        "type": "required"
      },
      {
        "type": "minLength",
        "value": 5
      }
    ]
  },
  {
    "type": "input",
    "name": "lastName",
    "placeholder": "Hernández",
    "label": "Last name",
    "value": "Tiago",
    "validations": [
      {
        "type": "required"
      }
    ]
  },
  {
    "type": "email",
    "name": "email",
    "placeholder": "deymerh@deymerh.co",
    "label": "Email",
    "value": "deyer1227@gmail.com",
    "validations": [
      {
        "type": "required"
      },
      {
        "type": "email"
      }
    ]
  },
  {
    "type": "select",
    "name": "favoriteGame",
    "label": "Favorite game",
    "value": "",
    "options": [
      {
        "id": 1,
        "label": "Super Smash"
      },
      {
        "id": 2,
        "label": "Metal Gear"
      },
      {
        "id": 3,
        "label": "Resident Evil"
      }
    ]
  }
]